replisync/__init__.py
replisync/config.py
replisync/consts.py
replisync/consumers.py
replisync/errors.py
replisync/helpers.py
replisync/pipeline.py
replisync/receivers.py
replisync/start.py
replisync-0.6.2.dist-info/METADATA
replisync-0.6.2.dist-info/WHEEL
replisync-0.6.2.dist-info/entry_points.txt
replisync-0.6.2.dist-info/top_level.txt
replisync-0.6.2.dist-info/RECORD
