Metadata-Version: 2.1
Name: replisync
Version: 0.6.2
Summary: Транслятор репликации в задачи Celery
Home-page: https://stash.bars-open.ru/projects/BUDG/repos/replisync
Author: BARS Group
Author-email: kirov@bars-open.ru
License: MIT
Platform: UNKNOWN
Classifier: Intended Audience :: Developers
Classifier: Environment :: Web Environment
Classifier: Natural Language :: Russian
Classifier: Natural Language :: English
Classifier: Operating System :: OS Independent
Classifier: Programming Language :: Python :: 3.6
Classifier: Programming Language :: Python :: 3.7
Classifier: Programming Language :: Python :: 3.8
Classifier: Programming Language :: Python :: 3.9
Classifier: Programming Language :: Python :: 3.10
Classifier: Programming Language :: Python :: 3.11
Classifier: License :: OSI Approved :: MIT License
Classifier: Development Status :: 5 - Production/Stable
Requires-Dist: psycopg2 (==2.9.1)
Requires-Dist: celery (==5.2.3)
